privatebinapi/__init__.py
privatebinapi/common.py
privatebinapi/deletion.py
privatebinapi/download.py
privatebinapi/exceptions.py
privatebinapi/upload.py
PrivateBinAPI-1.0.0.dist-info/LICENSE
PrivateBinAPI-1.0.0.dist-info/METADATA
PrivateBinAPI-1.0.0.dist-info/WHEEL
PrivateBinAPI-1.0.0.dist-info/top_level.txt
PrivateBinAPI-1.0.0.dist-info/RECORD
