Metadata-Version: 2.1
Name: PrivateBinAPI
Version: 1.0.0
Summary: A wrapper for the PrivateBin API
Home-page: https://github.com/Pioverpie/privatebin-api/
Author: Pioverpie
License: UNKNOWN
Project-URL: Source, https://github.com/Pioverpie/privatebin-api/
Project-URL: Issues, https://github.com/Pioverpie/privatebin-api/issues/
Keywords: privatebin pastebin
Platform: UNKNOWN
Classifier: Development Status :: 3 - Alpha
Classifier: Intended Audience :: Developers
Classifier: Programming Language :: Python :: 3
Classifier: License :: OSI Approved :: MIT License
Classifier: Operating System :: OS Independent
Classifier: Programming Language :: Python :: 3
Classifier: Programming Language :: Python :: 3.6
Classifier: Programming Language :: Python :: 3.7
Classifier: Programming Language :: Python :: 3.8
Classifier: Programming Language :: Python :: 3.9
Classifier: Topic :: Security :: Cryptography
Requires-Python: >=3.6
Requires-Dist: PBinCLI
Requires-Dist: requests
Requires-Dist: httpx
